pdfdata/__init__.py
pdfdata/flag_decomposer.py
pdfdata/parse_pdf.py
pdfdata/pdf_doc_extract_block_df.py
pdfdata/pdf_doc_extract_block_line_df.py
pdfdata/pdf_doc_extract_span_df.py
pdfdata/pdf_doc_extract_span_list.py
pdfdata/pdf_text_to_jsonnl.py
pdfdata-0.1.3.2.dist-info/LICENCE
pdfdata-0.1.3.2.dist-info/METADATA
pdfdata-0.1.3.2.dist-info/WHEEL
pdfdata-0.1.3.2.dist-info/top_level.txt
pdfdata-0.1.3.2.dist-info/RECORD
