Metadata-Version: 2.1
Name: pdfdata
Version: 0.1.3.2
Summary: Extracting text and data from PDFs
Home-page: https://github.com/petermeissner/pdfdata
Author: Peter Meissner
Author-email: retep.meissner@gmail.com
License: MIT
Platform: UNKNOWN
Classifier: Programming Language :: Python :: 3
Classifier: License :: OSI Approved :: MIT License
Classifier: Operating System :: OS Independent
Requires-Python: >=3.6
Requires-Dist: PyMuPDF
